[
    {
        "title": "Rules & Regulations",
        "subtitle": "Please Follow the rules and regulations",
        "icon": "/icons/rules.svg",
        "adminName": "rules",
        "redirect": "https://drive.google.com/file/d/1Em4mIpy9zsw6VBaXgovSYDhxxsYGXgO_/view?usp=sharing"
    },
    {
        "title": "Feedback Form",
        "subtitle": "Give your feedback here",
        "icon": "/icons/psform.svg",
        "adminName": "feedback-form",
        "redirect": "https://forms.gle/Mos8MPZ8C5LoEGWJ8"
    },
    {
        "title": "E-Certificates",
        "subtitle": "Tap here to Download your certificates",
        "icon": "/icons/certificates.svg",
        "adminName": "certificates"
    },
    { 
        "title": "Get Help",
        "subtitle": "We are one tap away from you",
        "icon": "/icons/get-help.svg",
        "link": "tel:8356876018",
        "adminName": "get-help"
    },
    { 
        "title": "Logout",
        "subtitle": "Tap here to logout from the app",
        "icon": "/icons/logout.svg",
        "logout": true
    }
]
